mcp_server_aidrac/__init__.py
mcp_server_aidrac/server.py
mcp_server_aidrac/bridges/__init__.py
mcp_server_aidrac/bridges/sentinel.py
mcp_server_aidrac/cli/__init__.py
mcp_server_aidrac/cli/dtmf.py
mcp_server_aidrac/cli/listen.py
mcp_server_aidrac/cli/main.py
mcp_server_aidrac/cli/notify.py
mcp_server_aidrac/cli/send.py
mcp_server_aidrac/cli/tone.py
mcp_server_aidrac/protocols/__init__.py
mcp_server_aidrac/protocols/dtmf.py
mcp_server_aidrac/protocols/ultrasonic.py
mcp_server_aidrac/transports/__init__.py
mcp_server_aidrac/transports/ipoll_bridge.py
mcp_server_aidrac/transports/ntfy.py
mcp_server_aidrac-0.2.0.dist-info/METADATA
mcp_server_aidrac-0.2.0.dist-info/WHEEL
mcp_server_aidrac-0.2.0.dist-info/entry_points.txt
mcp_server_aidrac-0.2.0.dist-info/RECORD
