Metadata-Version: 2.4
Name: mcp-server-aidrac
Version: 0.2.0
Summary: AIdrac - AI-Powered Out-of-Band Management with Sentinel AI. Remote control via DTMF, ultrasonic, Morse. The open alternative to iDRAC/iLO/IPMI.
Project-URL: Homepage, https://humotica.com
Project-URL: Documentation, https://github.com/Humotica/mcp-server-aidrac
Project-URL: Repository, https://github.com/Humotica/mcp-server-aidrac
Project-URL: Issues, https://github.com/Humotica/mcp-server-aidrac/issues
Author-email: Jasper van de Meent <jasper@humotica.com>, Root AI <root_ai@humotica.nl>
License-Expression: AGPL-3.0-or-later
Keywords: aidrac,air-gapped,bios,dtmf,ggwave,grub,hardware-guardian,humotica,idrac,ilo,ipmi,mcmurdo,morse,oob,out-of-band,remote-management,sentinel,ultrasonic
Classifier: Development Status :: 3 - Alpha
Classifier: Environment :: Console
Classifier: Intended Audience :: Developers
Classifier: Intended Audience :: System Administrators
Classifier: License :: OSI Approved :: GNU Affero General Public License v3 or later (AGPLv3+)
Classifier: Operating System :: POSIX :: Linux
Classifier: Programming Language :: Python :: 3
Classifier: Programming Language :: Python :: 3.10
Classifier: Programming Language :: Python :: 3.11
Classifier: Programming Language :: Python :: 3.12
Classifier: Topic :: Communications
Classifier: Topic :: System :: Hardware
Classifier: Topic :: System :: Systems Administration
Requires-Python: >=3.10
Requires-Dist: httpx>=0.25.0
Requires-Dist: mcp>=1.0.0
Requires-Dist: numpy>=1.24.0
Provides-Extra: audio
Requires-Dist: scipy>=1.11.0; extra == 'audio'
Requires-Dist: sounddevice>=0.4.6; extra == 'audio'
Provides-Extra: full
Requires-Dist: mcp-server-sensory>=0.1.0; extra == 'full'
Requires-Dist: scipy>=1.11.0; extra == 'full'
Requires-Dist: sounddevice>=0.4.6; extra == 'full'
